[
  {
    "name": "testar",
    "src": "/img1200/baispring_MG_0466.jpg",
    "id": "",
    "price": "",
    "compostion": "",
    "color": "",
    "product": ""
  },
  {
    "name": "",
    "src": "/img1200/baispring_MG_0535.jpg",
    "id": "",
    "price": "",
    "compostion": "",
    "color": "",
    "product": ""
  },
  {
    "name": "",
    "id": "",
    "price": "",
    "compostion": "",
    "color": "",
    "product": ""
  },
  {
    "name": "",
    "id": "",
    "price": "",
    "compostion": "",
    "color": "",
    "product": ""
  },
  {
    "name": "",
    "id": "",
    "price": "",
    "compostion": "",
    "color": "",
    "product": ""
  },
  {
    "name": "",
    "id": "",
    "price": "",
    "compostion": "",
    "color": "",
    "product": ""
  }
]
